RetrieverVectorDB/RetrieverVectorDB.py
RetrieverVectorDB/__init__.py
RetrieverVectorDB-0.5.dist-info/METADATA
RetrieverVectorDB-0.5.dist-info/WHEEL
RetrieverVectorDB-0.5.dist-info/top_level.txt
RetrieverVectorDB-0.5.dist-info/RECORD
